odoo/addons/purchase_tier_validation/README.rst
odoo/addons/purchase_tier_validation/__init__.py
odoo/addons/purchase_tier_validation/__manifest__.py
odoo/addons/purchase_tier_validation/i18n/es.po
odoo/addons/purchase_tier_validation/i18n/purchase_tier_validation.pot
odoo/addons/purchase_tier_validation/models/__init__.py
odoo/addons/purchase_tier_validation/models/purchase_order.py
odoo/addons/purchase_tier_validation/models/tier_definition.py
odoo/addons/purchase_tier_validation/static/description/icon.png
odoo/addons/purchase_tier_validation/views/purchase_order_view.xml
odoo11_addon_purchase_tier_validation-11.0.1.1.0.dist-info/METADATA
odoo11_addon_purchase_tier_validation-11.0.1.1.0.dist-info/RECORD
odoo11_addon_purchase_tier_validation-11.0.1.1.0.dist-info/WHEEL
odoo11_addon_purchase_tier_validation-11.0.1.1.0.dist-info/top_level.txt
